src/__init__.py
src/colors.py
src/config.py
src/main.py
gsec-1.0.1.dist-info/METADATA
gsec-1.0.1.dist-info/WHEEL
gsec-1.0.1.dist-info/entry_points.txt
gsec-1.0.1.dist-info/licenses/LICENSE
gsec-1.0.1.dist-info/RECORD
