Metadata-Version: 2.1
Name: gsec
Version: 1.0.1
Summary: Store secrets in a git repository. (Use under your OWN risk)
Project-URL: homepage, https://github.com/rooyca/git-secret
Project-URL: issues, https://github.com/rooyca/git-secret/issues
Author-email: rooyca <rooyca@gmail.com>
License: MIT
License-File: LICENSE
Classifier: License :: OSI Approved :: MIT License
Classifier: Operating System :: OS Independent
Classifier: Programming Language :: Python :: 3
Requires-Python: >=3.9
